{"inkVersion":21,"root":[[["^nya","\n","^nya.","\n",["^nya..","\n",["ev",{"^->":"0.g-0.g-1.2.$r1"},{"temp=":"$r"},"str",{"->":".^.s"},[{"#n":"$r1"}],"/str","/ev",{"*":".^.^.c-0","flg":2},{"s":["^nyaa",{"->":"$r","var":true},null]}],{"c-0":["ev",{"^->":"0.g-0.g-1.c-0.$r2"},"/ev",{"temp=":"$r"},{"->":".^.^.2.s"},[{"#n":"$r2"}],"\n",{"->":"0.g-2"},{"#f":5}],"#f":5,"#n":"g-1"}],{"#f":5,"#n":"g-0"}],{"g-2":["^nya?","\n","ev","str","^Nyaaaaa","/str","/ev",{"VAR=":"charname","re":true},"ev",1,"/ev",{"VAR=":"chimg","re":true},["^nya nya","\n","ev","str","^ebd1?","/str","/ev",{"*":".^.c-1","flg":4},"ev","str","^ebd2?","/str","/ev",{"*":".^.c-2","flg":4},"ev","str","^ebd3?","/str","/ev",{"*":".^.c-3","flg":4},{"c-1":["\n",{"->":"ebd1"},{"->":"0.g-4"},{"#f":5}],"c-2":["\n",{"->":"ebd1"},{"->":"0.g-4"},{"#f":5}],"c-3":["\n",{"->":"ebd1"},"end",{"->":"0.g-4"},{"#f":5}],"#f":5,"#n":"g-3"}],{"#f":5}],"g-4":["done",{"#f":5}]}],"done",{"ebd1":[[["^nyar.","\n",["ev",{"^->":"ebd1.0.g-0.2.$r1"},{"temp=":"$r"},"str",{"->":".^.s"},[{"#n":"$r1"}],"/str","/ev",{"*":".^.^.c-0","flg":18},{"s":["^ff",{"->":"$r","var":true},null]}],{"c-0":["ev",{"^->":"ebd1.0.g-0.c-0.$r2"},"/ev",{"temp=":"$r"},{"->":".^.^.2.s"},[{"#n":"$r2"}],"\n",{"->":"ebd1.0.g-1"},{"#f":5}],"#f":5,"#n":"g-0"}],{"g-1":["^neahehe. FREEDOM OF CHOICE.","\n","ev","str","^nya","/str","/ev",{"VAR=":"charname","re":true},"end",{"#f":5}]}],{"#f":1}],"ebd2":[[["^nyarf.","\n","end",{"#f":5,"#n":"g-0"}],null],{"#f":1}],"ebd3":[[["^nyaf.","\n","end",{"#f":5,"#n":"g-0"}],null],{"#f":1}],"global decl":["ev","str","^nya","/str",{"VAR=":"charname"},0,{"VAR=":"chimg"},"/ev","end",null],"#f":1}],"listDefs":{}}